MANIFEST.in
README.rst
setup.cfg
setup.py
docs/HISTORY.txt
docs/INSTALL.txt
docs/LICENSE.GPL
docs/LICENSE.txt
plomino/__init__.py
plomino/__init__.pyc
plomino.tinymce.egg-info/PKG-INFO
plomino.tinymce.egg-info/SOURCES.txt
plomino.tinymce.egg-info/dependency_links.txt
plomino.tinymce.egg-info/entry_points.txt
plomino.tinymce.egg-info/namespace_packages.txt
plomino.tinymce.egg-info/not-zip-safe
plomino.tinymce.egg-info/requires.txt
plomino.tinymce.egg-info/top_level.txt
plomino/tinymce/__init__.py
plomino/tinymce/configure.zcml
plomino/tinymce/profiles.zcml
plomino/tinymce/tests.py
plomino/tinymce/browser/__init__.py
plomino/tinymce/browser/action.pt
plomino/tinymce/browser/action.py
plomino/tinymce/browser/cache.pt
plomino/tinymce/browser/cache.py
plomino/tinymce/browser/configure.zcml
plomino/tinymce/browser/error.pt
plomino/tinymce/browser/field.pt
plomino/tinymce/browser/field.py
plomino/tinymce/browser/form.py
plomino/tinymce/browser/hidewhen.pt
plomino/tinymce/browser/hidewhen.py
plomino/tinymce/browser/subform.pt
plomino/tinymce/browser/valid.pt
plomino/tinymce/browser/view.py
plomino/tinymce/browser/tinymce_plugins/mountme.js
plomino/tinymce/browser/tinymce_plugins/atomic/README.txt
plomino/tinymce/browser/tinymce_plugins/atomic/editor_plugin.js
plomino/tinymce/browser/tinymce_plugins/atomic/editor_plugin_src.js
plomino/tinymce/browser/tinymce_plugins/plomino_accordion/add_accordion.htm.pt
plomino/tinymce/browser/tinymce_plugins/plomino_accordion/editor_plugin.js
plomino/tinymce/browser/tinymce_plugins/plomino_accordion/img/AUTHORS
plomino/tinymce/browser/tinymce_plugins/plomino_accordion/img/README.txt
plomino/tinymce/browser/tinymce_plugins/plomino_accordion/img/add_accordion.png
plomino/tinymce/browser/tinymce_plugins/plomino_accordion/img/copyright
plomino/tinymce/browser/tinymce_plugins/plomino_accordion/js/add_accordion.js
plomino/tinymce/browser/tinymce_plugins/plomino_tinymce/editor_plugin.js
plomino/tinymce/browser/tinymce_plugins/plomino_tinymce/css/plomino.tinymce.css
plomino/tinymce/browser/tinymce_plugins/plomino_tinymce/img/AUTHORS
plomino/tinymce/browser/tinymce_plugins/plomino_tinymce/img/PlominoAction.png
plomino/tinymce/browser/tinymce_plugins/plomino_tinymce/img/PlominoCache.png
plomino/tinymce/browser/tinymce_plugins/plomino_tinymce/img/PlominoField.png
