Metadata-Version: 1.1
Name: plomino.tinymce
Version: 0.7.3
Summary: TinyMCE Plomino Embedded Plugin
Home-page: http://pypi.python.org/pypi/plomino.tinymce
Author: Romaric BREIL
Author-email: romaric.breil@supinfo.com
License: GPL
Platform: UNKNOWN
Classifier: Framework :: Plone
Classifier: Programming Language :: Python
